channelflowlib/__init__.py
channelflowlib/constants.py
channelflowlib/critical_flow.py
channelflowlib/gvf.py
channelflowlib/openchannellib.py
channelflowlib-0.9.1.dist-info/LICENSE
channelflowlib-0.9.1.dist-info/METADATA
channelflowlib-0.9.1.dist-info/WHEEL
channelflowlib-0.9.1.dist-info/top_level.txt
channelflowlib-0.9.1.dist-info/RECORD
