Metadata-Version: 2.1
Name: channelflowlib
Version: 0.9.1
Summary: Python library for open channel flow and hydraulics engineering calculations.
Home-page: https://github.com/alexiusacademia/ChannelFlowLib
Author: Alexius Academia
Author-email: alexius.sayco.academia@gmail.com
License: GNU GPL 3
Keywords: hydraulics open-channel fluid-flow
Classifier: Development Status :: 4 - Beta
Classifier: Intended Audience :: Science/Research
Classifier: Natural Language :: English
Classifier: Operating System :: OS Independent
Classifier: Programming Language :: Python
Classifier: Programming Language :: Python :: 2.7
Classifier: Programming Language :: Python :: 3.4
Classifier: Programming Language :: Python :: 3.5
Classifier: Programming Language :: Python :: 3.6
License-File: LICENSE
